README.md
setup.cfg
setup.py
beambending/__init__.py
beambending/beam.py
beambending.egg-info/PKG-INFO
beambending.egg-info/SOURCES.txt
beambending.egg-info/dependency_links.txt
beambending.egg-info/requires.txt
beambending.egg-info/top_level.txt
beambending.egg-info/zip-safe
test/test_beam.py