Metadata-Version: 2.1
Name: beambending
Version: 1.1.0
Summary: Educational package for visualizing shear forces and bending moments on 1-D beams
Home-page: https://github.com/alfredocarella/simplebendingpractice
Author: Alfredo Carella
Author-email: alfredocarella@gmail.com
License: cc-by-4.0
Download-URL: https://github.com/alfredocarella/simplebendingpractice/archive/1.1.0.tar.gz
Platform: UNKNOWN
Classifier: Development Status :: 4 - Beta
Classifier: Programming Language :: Python :: 3
